setup.py
asposestorage.egg-info/PKG-INFO
asposestorage.egg-info/SOURCES.txt
asposestorage.egg-info/dependency_links.txt
asposestorage.egg-info/top_level.txt
models/DateTime.py
models/DiscUsage.py
models/DiscUsageResponse.py
models/FileExist.py
models/FileExistResponse.py
models/FileVersion.py
models/FileVersionsResponse.py
models/MoveFileResponse.py
models/MoveFolderResponse.py
models/RemoveFileResponse.py
models/RemoveFolderResponse.py
models/ResponseMessage.py
models/StorageExistResponse.py
models/__init__.py
test/__init__.py
test/test.py