Metadata-Version: 1.1
Name: asposestorage
Version: 1.0
Summary: Aspose Cloud SDK for Python allows you to use Aspose API in your Python applications
Home-page: http://www.aspose.com
Author: Imran Anwar
Author-email: imranwar@gmail.com
License: UNKNOWN
Platform: UNKNOWN
Classifier: Programming Language :: Python
Classifier: Programming Language :: Python :: 2
Classifier: License :: OSI Approved :: MIT License
Classifier: Operating System :: OS Independent
